aioli/__init__.py
aioli/__version__.py
aioli/ezua__version__.py
aioli/util.py
aioli/cli/__init__.py
aioli/cli/__main__.py
aioli/cli/_util.py
aioli/cli/cli.py
aioli/cli/deployment.py
aioli/cli/errors.py
aioli/cli/model.py
aioli/cli/project.py
aioli/cli/registry.py
aioli/cli/render.py
aioli/cli/sso.py
aioli/cli/template.py
aioli/cli/version.py
aioli/cli/test/conftest.py
aioli/cli/test/test_cli.py
aioli/common/__init__.py
aioli/common/check.py
aioli/common/constants.py
aioli/common/declarative_argparse.py
aioli/common/requests.py
aioli/common/util.py
aioli/common/api/__init__.py
aioli/common/api/_util.py
aioli/common/api/authentication.py
aioli/common/api/certs.py
aioli/common/api/errors.py
aioli/common/api/request.py
aiolirest/__init__.py
aiolirest/api_client.py
aiolirest/api_response.py
aiolirest/configuration.py
aiolirest/exceptions.py
aiolirest/py.typed
aiolirest/rest.py
aiolirest/api/__init__.py
aiolirest/api/deployments_api.py
aiolirest/api/information_api.py
aiolirest/api/packaged_models_api.py
aiolirest/api/projects_api.py
aiolirest/api/registries_api.py
aiolirest/api/roles_api.py
aiolirest/api/templates_api.py
aiolirest/api/users_api.py
aiolirest/models/__init__.py
aiolirest/models/auto_scaling_template.py
aiolirest/models/auto_scaling_template_request.py
aiolirest/models/autoscaling.py
aiolirest/models/configuration_resources.py
aiolirest/models/controller_config.py
aiolirest/models/controller_status.py
aiolirest/models/deployment.py
aiolirest/models/deployment_model_version.py
aiolirest/models/deployment_priority.py
aiolirest/models/deployment_request.py
aiolirest/models/deployment_state.py
aiolirest/models/error_response.py
aiolirest/models/event_info.py
aiolirest/models/ezua_info.py
aiolirest/models/failure_info.py
aiolirest/models/model_response.py
aiolirest/models/observability.py
aiolirest/models/packaged_model.py
aiolirest/models/packaged_model_request.py
aiolirest/models/project.py
aiolirest/models/resource_profile.py
aioli_sdk-1.10.0.dist-info/METADATA
aioli_sdk-1.10.0.dist-info/WHEEL
aioli_sdk-1.10.0.dist-info/entry_points.txt
aioli_sdk-1.10.0.dist-info/top_level.txt
aioli_sdk-1.10.0.dist-info/RECORD
