Metadata-Version: 2.4
Name: aioli-sdk
Version: 1.10.0
Summary: Aioli (AI OnLine Inference), a platform for deploying AI models at scale.
Home-page: https://github.com/determined-ai/aioli
Author: HPE AI Solutions
License: Apache License 2.0
Requires-Python: >=3.8
Requires-Dist: packaging
Requires-Dist: numpy>=1.16.2
Requires-Dist: psutil
Requires-Dist: pyzmq>=18.1.0
Requires-Dist: certifi
Requires-Dist: filelock
Requires-Dist: requests
Requires-Dist: lomond>=0.3.3
Requires-Dist: pathspec>=0.6.0
Requires-Dist: termcolor>=1.1.0
Requires-Dist: oschmod; platform_system == "Windows"
Requires-Dist: argcomplete>=1.9.4
Requires-Dist: gitpython>=3.1.3
Requires-Dist: pyOpenSSL>=19.1.0
Requires-Dist: python-dateutil
Requires-Dist: pytz
Requires-Dist: tabulate>=0.8.3
Requires-Dist: ruamel.yaml>=0.15.29
Requires-Dist: docker[ssh]>=3.7.3
Requires-Dist: paramiko>=2.4.2
Requires-Dist: tqdm
Requires-Dist: appdirs
Requires-Dist: analytics-python
Requires-Dist: urllib3<2.3.0,>=2.0.0
Requires-Dist: pydantic>=2
Requires-Dist: typing-extensions>=4.7.1
Requires-Dist: pytest>=7.4.4
Requires-Dist: pytest-cov>=4.1.0
Requires-Dist: pexpect>=4.9.0
Dynamic: author
Dynamic: description
Dynamic: description-content-type
Dynamic: home-page
Dynamic: license
Dynamic: requires-dist
Dynamic: requires-python
Dynamic: summary
